{
  "properties": {
    "connectionReferences": {
      "shared_sharepointonline_1": {
        "runtimeSource": "embedded",
        "connection": {
          "connectionReferenceLogicalName": "invoicet_SharePoint"
        },
        "api": {
          "name": "shared_sharepointonline"
        }
      }
    },
    "definition": {
      "$schema": "https://schema.management.azure.com/providers/Microsoft.Logic/schemas/2016-06-01/workflowdefinition.json#",
      "contentVersion": "1.0.0.0",
      "parameters": {
        "$connections": {
          "defaultValue": {},
          "type": "Object"
        },
        "$authentication": {
          "defaultValue": {},
          "type": "SecureObject"
        },
        "InvoiceTrackingSite (invoicet_InvoiceTrackingSite)": {
          "defaultValue": "https://cdph.sharepoint.com/sites/InvoiceTrackingDev",
          "type": "String",
          "metadata": {
            "schemaName": "invoicet_InvoiceTrackingSite"
          }
        },
        "InvoiceTrackingInvoices (invoicet_InvoiceTrackingInvoices)": {
          "defaultValue": "Invoice Tracking",
          "type": "String",
          "metadata": {
            "schemaName": "invoicet_InvoiceTrackingInvoices"
          }
        }
      },
      "triggers": {
        "When_an_item_is_created": {
          "recurrence": {
            "interval": 1,
            "frequency": "Minute"
          },
          "splitOn": "@triggerOutputs()?['body/value']",
          "metadata": {
            "operationMetadataId": "6bbc15cf-186a-45bc-8623-ffa81664259d"
          },
          "type": "OpenApiConnection",
          "inputs": {
            "host": {
              "connectionName": "shared_sharepointonline_1",
              "operationId": "GetOnNewItems",
              "apiId": "/providers/Microsoft.PowerApps/apis/shared_sharepointonline"
            },
            "parameters": {
              "dataset": "@parameters('InvoiceTrackingSite (invoicet_InvoiceTrackingSite)')",
              "table": "@parameters('InvoiceTrackingInvoices (invoicet_InvoiceTrackingInvoices)')"
            },
            "authentication": "@parameters('$authentication')"
          }
        }
      },
      "actions": {
        "Condition": {
          "actions": {
            "Update_item": {
              "runAfter": {},
              "metadata": {
                "operationMetadataId": "d17e2330-607f-4626-a3e4-f132fcbb85f2"
              },
              "type": "OpenApiConnection",
              "inputs": {
                "host": {
                  "connectionName": "shared_sharepointonline_1",
                  "operationId": "PatchItem",
                  "apiId": "/providers/Microsoft.PowerApps/apis/shared_sharepointonline"
                },
                "parameters": {
                  "dataset": "@parameters('InvoiceTrackingSite (invoicet_InvoiceTrackingSite)')",
                  "table": "@parameters('InvoiceTrackingInvoices (invoicet_InvoiceTrackingInvoices)')",
                  "id": "@triggerOutputs()?['body/ID']",
                  "item/Title": "@triggerOutputs()?['body/Title']",
                  "item/StaffName/Value": "Drill 2: Reverting Appropriations Invoice"
                },
                "authentication": "@parameters('$authentication')"
              }
            }
          },
          "runAfter": {},
          "expression": {
            "equals": [
              "@triggerOutputs()?['body/Drill_x0020_2']",
              "@true"
            ]
          },
          "metadata": {
            "operationMetadataId": "0abfedb7-76da-478a-bed1-e060c1e93d59"
          },
          "type": "If"
        }
      }
    },
    "templateName": ""
  },
  "schemaVersion": "1.0.0.0"
}